harpy/__init__.py
harpy/__main__.py
harpy/__version__.py
harpy/argtypes.py
harpy/cli.py
harpy/consts.py
harpy/db.json
harpy/globs.py
harpy/handlers.py
harpy/net.py
harpy/utils.py
project.harpy-0.0.11.dist-info/LICENSE
project.harpy-0.0.11.dist-info/METADATA
project.harpy-0.0.11.dist-info/WHEEL
project.harpy-0.0.11.dist-info/entry_points.txt
project.harpy-0.0.11.dist-info/top_level.txt
project.harpy-0.0.11.dist-info/RECORD
