Metadata-Version: 2.1
Name: project.harpy
Version: 0.0.11
Summary: Active/passive ARP discovery tool
Author: Serhat Çelik
License: MIT
Keywords: harpy,arp,discovery
Classifier: Development Status :: 5 - Production/Stable
Classifier: Environment :: Console
Classifier: Intended Audience :: Information Technology
Classifier: License :: OSI Approved :: MIT License
Classifier: Programming Language :: Python :: 3
Classifier: Programming Language :: Python :: 3 :: Only
Classifier: Topic :: System :: Networking
Classifier: Topic :: System :: Networking :: Monitoring
Requires-Python: ~=3.9
License-File: LICENSE
